anodot_monitor/__init__.py
anodot_monitor/anodot_reporter.py
anodot_monitor/base_properties.py
anodot_monitor/metric_name.py
anodot_monitor/metric_registry.py
anodot_monitor/metrics_adapter.py
anodot_monitor/reporting_client.py
anodot_monitor/settings.py
anodot_monitor-0.9.dist-info/LICENSE
anodot_monitor-0.9.dist-info/METADATA
anodot_monitor-0.9.dist-info/WHEEL
anodot_monitor-0.9.dist-info/top_level.txt
anodot_monitor-0.9.dist-info/RECORD
