Metadata-Version: 2.1
Name: anodot-monitor
Version: 0.9
Summary: Anodot Monitoring
Author: Alexander Shereshevsky
Author-email: shereshevsky@gmail.com
License-File: LICENSE
Requires-Dist: pyformance
Requires-Dist: requests
Requires-Dist: more-itertools
Requires-Dist: loguru
